soramimi_phonetic_search_dataset/__init__.py
soramimi_phonetic_search_dataset/dataset.py
soramimi_phonetic_search_dataset/evaluate.py
soramimi_phonetic_search_dataset/evaluate_phonetic_search_dataset.py
soramimi_phonetic_search_dataset/py.typed
soramimi_phonetic_search_dataset/ranking.py
soramimi_phonetic_search_dataset/schemas.py
soramimi_phonetic_search_dataset/data/LICENSE
soramimi_phonetic_search_dataset/data/baseball.json
soramimi_phonetic_search_dataset-0.0.9.dist-info/METADATA
soramimi_phonetic_search_dataset-0.0.9.dist-info/WHEEL
soramimi_phonetic_search_dataset-0.0.9.dist-info/licenses/LICENSE-CODE
soramimi_phonetic_search_dataset-0.0.9.dist-info/RECORD
