Metadata-Version: 2.4
Name: soramimi-phonetic-search-dataset
Version: 0.0.9
Summary: 音韻的類似性を考慮した検索システムの評価用データセット。替え歌の歌詞から構築された特定ジャンルの単語ペアを収録。
Project-URL: Homepage, https://github.com/jiroshimaya/soramimi-phonetic-search-dataset
Author: shimajiroxyz
License: MIT AND CDLA-Permissive-2.0
License-File: LICENSE-CODE
Keywords: Japanese,dataset,phonetic-search,あいまい検索,替え歌,評価用データセット,音韻検索,音韻類似性
Classifier: License :: OSI Approved :: MIT License
Classifier: Operating System :: OS Independent
Classifier: Programming Language :: Python :: 3.11
Requires-Python: >=3.11
Requires-Dist: editdistance>=0.8.1
Requires-Dist: jamorasep>=0.0.1
Requires-Dist: kanasim>=0.0.4
Requires-Dist: litellm>=1.63.3
Requires-Dist: pyopenjtalk>=0.4.0
Requires-Dist: python-dotenv>=1.0.1
Requires-Dist: tqdm>=4.67.1
